{
    "backend": "api-server-nodejs",
    "db_name": "",
    "db_pass": "",
    "db_type": "sqlite",
    "db_user": "",
    "dbms": "1",
    "description": "generated product",
    "design": "soft-ui-dashboard",
    "docker": "1",
    "err_code": 0,
    "frontend": "react",
    "heroku": "0",
    "pattern": "fullstack",
    "pro": "0",
    "task_id": "b9c24575-d395-415d-99b2-2add8e675657",
    "task_info": "Upload Sources [0%] - 291 files",
    "task_output": "b9c24575-d395-415d-99b2-2add8e675657.zip",
    "task_result": "SUCCESS",
    "task_state": "RUNNING",
    "task_ts_end": "2024-02-03-21-44-31",
    "task_ts_start": "2024-02-03-21-44-30"
}